quarrel_solver/__init__.py
quarrel_solver/__main__.py
quarrel_solver/wordlist.json
quarrel_solver-1.12.dist-info/LICENSE
quarrel_solver-1.12.dist-info/METADATA
quarrel_solver-1.12.dist-info/WHEEL
quarrel_solver-1.12.dist-info/top_level.txt
quarrel_solver-1.12.dist-info/zip-safe
quarrel_solver-1.12.dist-info/RECORD
