Metadata-Version: 2.1
Name: quarrel-solver
Version: 1.12
Summary: Tool for Quarrel (video game)
Home-page: https://github.com/silvncr/quarrel
Author: silvncr
License: MIT
Classifier: Programming Language :: Python
Classifier: Programming Language :: Python :: 3
Classifier: Topic :: Games/Entertainment :: Board Games
Classifier: Topic :: Games/Entertainment :: Puzzle Games
Classifier: Topic :: Software Development :: Libraries
Classifier: Topic :: Software Development :: Libraries :: Python Modules
Requires-Python: >=3.6
License-File: LICENSE
